get_cli/__init__.py
get_cli/__main__.py
get_cli/cli.py
get_cli/constants.py
get_cli/controller.py
get_cli/main.py
get_cli/service.py
get_cli/storage.py
get_cli-0.1.4.dist-info/LICENSE
get_cli-0.1.4.dist-info/METADATA
get_cli-0.1.4.dist-info/WHEEL
get_cli-0.1.4.dist-info/entry_points.txt
get_cli-0.1.4.dist-info/RECORD
