Metadata-Version: 2.1
Name: get-cli
Version: 0.1.4
Summary: A simple unsafe cli tool to store and fetch data locally.
Home-page: https://github.com/noamtamir/get-cli
License: MIT
Author: noamtamir
Author-email: noam.tamir@gmail.com
Requires-Python: >=3.8,<4.0
Classifier: License :: OSI Approved :: MIT License
Classifier: Programming Language :: Python :: 3
Classifier: Programming Language :: Python :: 3.8
Classifier: Programming Language :: Python :: 3.9
Classifier: Programming Language :: Python :: 3.10
Classifier: Programming Language :: Python :: 3.11
Requires-Dist: pyperclip (>=1.8.2,<2.0.0)
Requires-Dist: pyyaml (>=6.0,<7.0)
Requires-Dist: typer[all] (>=0.7.0,<0.8.0)
Project-URL: Repository, https://github.com/noamtamir/get-cli
